MANIFEST.in
setup.py
geocity/__init__.py
geocity/cities.txt
geocity.egg-info/PKG-INFO
geocity.egg-info/SOURCES.txt
geocity.egg-info/dependency_links.txt
geocity.egg-info/not-zip-safe
geocity.egg-info/top_level.txt