Metadata-Version: 1.0
Name: geocity
Version: 0.1
Summary: offline geo city data
Home-page: https://github.com/royi1000/pycity
Author: Royi Reshef
Author-email: roy.myapp@gmail.com
License: MIT
Platform: UNKNOWN
